realtabformer/VERSION
realtabformer/__init__.py
realtabformer/__main__.py
realtabformer/data_utils.py
realtabformer/realtabformer.py
realtabformer/rtf_analyze.py
realtabformer/rtf_datacollator.py
realtabformer/rtf_exceptions.py
realtabformer/rtf_sampler.py
realtabformer/rtf_tokenizer.py
realtabformer/rtf_trainer.py
realtabformer/rtf_validators.py
realtabformer-0.2.4.dist-info/LICENSE
realtabformer-0.2.4.dist-info/METADATA
realtabformer-0.2.4.dist-info/WHEEL
realtabformer-0.2.4.dist-info/entry_points.txt
realtabformer-0.2.4.dist-info/RECORD
