Metadata-Version: 2.1
Name: realtabformer
Version: 0.2.4
Summary: A novel method for generating tabular and relational data using language models.
Home-page: https://github.com/avsolatorio/REaLTabFormer
License: MIT
Keywords: REaLTabFormer,deep learning,tabular data,transformers,data generation,seq2seq model,synthetic data,pytorch,language models,synthetic data generation
Author: Aivin V. Solatorio
Author-email: asolatorio@worldbank.org
Requires-Python: >=3.8
Classifier: License :: OSI Approved :: MIT License
Classifier: Operating System :: OS Independent
Classifier: Programming Language :: Python :: 3
Classifier: Programming Language :: Python :: 3.8
Classifier: Programming Language :: Python :: 3.9
Classifier: Programming Language :: Python :: 3.10
Classifier: Programming Language :: Python :: 3.11
Classifier: Programming Language :: Python :: 3
Requires-Dist: datasets (>=2.6.1)
Requires-Dist: numpy (>=1.21.6)
Requires-Dist: pandas (>=1.3.5)
Requires-Dist: scikit-learn (>=1.0.2)
Requires-Dist: shapely (>=1.8.5.post1)
Requires-Dist: tqdm (>=4.64.1)
Requires-Dist: transformers[sentencepiece,torch] (>=4.46.0)
Project-URL: Documentation, https://avsolatorio.github.io/REaLTabFormer/
